discord_cooldown/__init__.py
discord_cooldown/cooldown.py
discord_cooldown/modules.py
discord_cooldown-0.1.4.dist-info/LICENSE
discord_cooldown-0.1.4.dist-info/METADATA
discord_cooldown-0.1.4.dist-info/WHEEL
discord_cooldown-0.1.4.dist-info/top_level.txt
discord_cooldown-0.1.4.dist-info/RECORD
