Metadata-Version: 2.1
Name: discord-cooldown
Version: 0.1.4
Summary: Custom Cooldowns for discord Bot commands
Home-page: https://github.com/Modern-Realm/discord_cooldown
Author: P. Sai Keerthan Reddy
Author-email: saikeerthan.keerthan.9@gmail.com
License: MIT
Project-URL: Documentation, https://modern-realm.github.io/discord_cooldown/
Project-URL: Bug Tracker, https://github.com/Modern-Realm/discord_cooldown/issues
Project-URL: Examples, https://github.com/Modern-Realm/discord_cooldown/tree/main/Examples
Project-URL: Source, https://github.com/Modern-Realm/discord_cooldown/tree/main/package/discord_cooldown
Project-URL: Discord Server, https://discord.gg/GVMWx5EaAN
Keywords: cooldown,custom-cooldown,cooldowns,py-cord,nextcord,disnake,discordpy
Classifier: Development Status :: 5 - Production/Stable
Classifier: Intended Audience :: Developers
Classifier: Programming Language :: Python :: 3.8
Classifier: License :: OSI Approved :: MIT License
Classifier: Operating System :: OS Independent
Classifier: Natural Language :: English
Classifier: Topic :: Internet
Classifier: Topic :: Software Development
Classifier: Topic :: Software Development :: Libraries
Classifier: Topic :: Software Development :: Libraries :: Python Modules
Classifier: Typing :: Typed
Requires-Python: >=3.8
License-File: LICENSE
Requires-Dist: mysql-connector-python (>=8.0.28)
Requires-Dist: psycopg2-binary (>=2.9.3)
Requires-Dist: psycopg2 (>=2.9.5)
